phi_finder/__init__.py
phi_finder/_version.py
phi_finder/dicom_tools/__init__.py
phi_finder/dicom_tools/anonymise_dicom.py
phi_finder/dicom_tools/suburbs_australia.txt
phi_finder/dicom_tools/utils.py
phi_finder-2025.8.1.dist-info/METADATA
phi_finder-2025.8.1.dist-info/WHEEL
phi_finder-2025.8.1.dist-info/RECORD
